{
  "editions": [
    {
      "date": "2026-03-12",
      "type": "woman",
      "mainFeature": "margaret-ekpo",
      "alsoRead": [
        "why-economic-independence-changes-everything",
        "a-conversation-with-my-father"
      ],
      "region": "West Africa",
      "subject": "Meet the woman who organised Nigeria's women for independence"
    },
    {
      "date": "2026-03-12",
      "type": "article",
      "mainFeature": "daughters-of-independence",
      "alsoRead": [
        "bolanle-awe",
        "mariama-ba"
      ],
      "region": null,
      "subject": "Remembering the Women Behind African Independence"
    },
    {
      "date": "2026-03-12",
      "type": "woman",
      "mainFeature": "hatshepsut",
      "alsoRead": [
        "why-african-womens-stories-belong-in-every-classroom",
        "what-is-patriarchy"
      ],
      "region": "North Africa",
      "subject": "The queen they tried to erase from history"
    }
  ]
}
